pyDANETLSA/__init__.py
pyDANETLSA/monitor.py
pyDANETLSA/tests.py
pyDANETLSA/libs/__init__.py
pyDANETLSA/libs/configuration.py
pyDANETLSA/libs/dnstools.py
pyDANETLSA/libs/funcs.py
pyDANETLSA-1.0.10.dist-info/LICENSE
pyDANETLSA-1.0.10.dist-info/METADATA
pyDANETLSA-1.0.10.dist-info/WHEEL
pyDANETLSA-1.0.10.dist-info/top_level.txt
pyDANETLSA-1.0.10.dist-info/RECORD
