Metadata-Version: 2.2
Name: pyDANETLSA
Version: 1.0.10
Summary: Python library to generate a TLSA record format based on the active certificate on a host.
Author-email: Oscar Koeroo <okoeroo@gmail.com>
License: MIT
Project-URL: Homepage, https://github.com/okoeroo/pyDANETLSA
Project-URL: Repository, https://github.com/okoeroo/pyDANETLSA
Project-URL: Issues, https://github.com/okoeroo/pyDANETLSA/issues
Keywords: DANE,TLSA,X.509,X509,certificate
Classifier: Programming Language :: Python :: 3
Classifier: License :: OSI Approved :: MIT License
Classifier: Operating System :: OS Independent
Requires-Python: >=3.8
License-File: LICENSE
Requires-Dist: cryptography
Requires-Dist: pyOpenSSL
Requires-Dist: requests
Requires-Dist: dnspython
